<?xml version="1.0" encoding="euc-kr"?>
<vocab><word><text>
slept</text><definition>Àä´Ù</definition><date-of-entry>1386565983492</date-of-entry><reading-level>0</reading-level><writing-level>0</writing-level><id>-7568994875375819444</id></word><word><text>
studied</text><definition>°øºÎÇß´Ù</definition><date-of-entry>1386565983492</date-of-entry><reading-level>0</reading-level><writing-level>0</writing-level><id>4323685214431267890</id></word><word><text>played</text><definition>³î¾Ò´Ù</definition><date-of-entry>1386565983492</date-of-entry><reading-level>0</reading-level><writing-level>0</writing-level><id>-4589048710055424244</id></word><word><text>
rode</text><definition>ÅÀ´Ù</definition><date-of-entry>1386565983492</date-of-entry><reading-level>0</reading-level><writing-level>0</writing-level><id>-2458362807679437660</id></word><word><text>
bought</text><definition>½Õ´Ù</definition><date-of-entry>1386565983492</date-of-entry><reading-level>0</reading-level><writing-level>0</writing-level><id>1019521921704369072</id></word><word><text>
ate</text><definition>¸Ô¾ú´Ù</definition><date-of-entry>1386565983492</date-of-entry><reading-level>0</reading-level><writing-level>0</writing-level><id>5784317659585447927</id></word></vocab>
